pyvoc/__init__.py
pyvoc/check_config.py
pyvoc/dmanager.py
pyvoc/pyvoc.py
pyvoc/settings.py
pyvoc/termoutput.py
pyvoc-1.4.0.dist-info/LICENSE
pyvoc-1.4.0.dist-info/METADATA
pyvoc-1.4.0.dist-info/WHEEL
pyvoc-1.4.0.dist-info/entry_points.txt
pyvoc-1.4.0.dist-info/top_level.txt
pyvoc-1.4.0.dist-info/RECORD
