Metadata-Version: 2.1
Name: pyvoc
Version: 1.4.0
Summary: cross-platform dictionary and vocabulary building command line tool.
Home-page: http://github.com/makkoncept/pyvoc
Author: Mayank Nader
Author-email: nader.mayank@gmail.com
License: MIT
Platform: UNKNOWN
